{
  "name": "herbal_lang_b",
  "description": "Herbal section, Language B",
  "page_count": 32,
  "transitions": {
    "^|p": 54,
    "y|$": 1576,
    "p|S": 9,
    "S|6": 184,
    "6|o": 197,
    "o|k": 539,
    "k|y": 106,
    "^|o": 819,
    "r|$": 578,
    "o|d": 248,
    "d|a": 434,
    "a|2": 402,
    "2|r": 16,
    "^|q": 341,
    "q|o": 334,
    "o|y": 9,
    "d|$": 71,
    "o|f": 29,
    "f|S": 3,
    "S|o": 52,
    "^|C": 586,
    "C|y": 62,
    "y|p": 19,
    "p|C": 71,
    "C|6": 408,
    "6|y": 138,
    "^|y": 264,
    "6|d": 453,
    "d|y": 949,
    "^|a": 249,
    "n|$": 519,
    "a|1": 178,
    "1|n": 115,
    "o|$": 62,
    "C|o": 100,
    "f|o": 7,
    "6|p": 16,
    "p|d": 5,
    "^^^^|p": 17,
    "^^^|p": 30,
    "^^|p": 39,
    "y|$$": 145,
    "^|d": 348,
    "d|C": 27,
    "2|n": 386,
    "a|d": 7,
    "d|7": 5,
    "7|o": 43,
    "y|k": 126,
    "k|6": 226,
    "6|T": 6,
    "T|6": 17,
    "y|t": 82,
    "t|6": 116,
    "^|l": 59,
    "s|$": 144,
    "l|s": 16,
    "^^|d": 60,
    "s|$$": 17,
    "o|a": 14,
    "^|S": 265,
    "S|T": 4,
    "T|y": 28,
    "^|T": 19,
    "o|l": 314,
    "l|o": 42,
    "k|7": 137,
    "7|d": 107,
    "l|C": 40,
    "l|$": 318,
    "a|l": 265,
    "S|7": 36,
    "7|y": 77,
    "^|s": 89,
    "^^|o": 33,
    "o|s": 43,
    "6|k": 97,
    "m|$": 116,
    "a|m": 111,
    "l|d": 60,
    "^^|q": 27,
    "s|a": 39,
    "^|7": 4,
    "^^|s": 22,
    "^|r": 12,
    "r|C": 7,
    "^^|r": 1,
    "y|$$$": 38,
    "a|r": 408,
    "C|s": 6,
    "s|6": 3,
    "d|s": 2,
    "a|$": 4,
    "S|a": 5,
    "p|$": 5,
    "y|f": 12,
    "f|C": 39,
    "r|$$": 27,
    "o|t": 242,
    "t|7": 40,
    "k|$": 20,
    "^|t": 138,
    "t|C": 80,
    "o|S": 4,
    "S|y": 23,
    "C|d": 227,
    "C|K": 54,
    "K|y": 69,
    "7|C": 2,
    "^^|t": 78,
    "6|$": 10,
    "6|s": 16,
    "t|a": 139,
    "^^|S": 15,
    "l|$$": 21,
    "l|$$$": 6,
    "l|$$$$": 3,
    "r|y": 17,
    "a|3": 11,
    "3|n": 13,
    "C|7": 44,
    "7|t": 5,
    "t|y": 43,
    "1|r": 51,
    "o|p": 36,
    "p|y": 8,
    "S|d": 44,
    "r|a": 38,
    "^|6": 7,
    "6|t": 23,
    "o|r": 179,
    "1|6": 1,
    "l|y": 42,
    "y|s": 3,
    "p|a": 23,
    "k|C": 91,
    "^|g": 1,
    "g|$": 14,
    "g|$$": 13,
    "y|K": 2,
    "K|6": 19,
    "d|o": 41,
    "k|a": 387,
    "^^|y": 68,
    "n|$$": 55,
    "k|o": 48,
    "t|o": 62,
    "o|7": 6,
    "^|k": 160,
    "s|C": 3,
    "7|k": 11,
    "t|$": 7,
    "o|6": 15,
    "7|s": 17,
    "C|k": 26,
    "k|8": 8,
    "8|y": 8,
    "y|S": 8,
    "6|S": 5,
    "p|6": 1,
    "y|d": 17,
    "y|$$$$": 19,
    "d|6": 5,
    "7|$": 9,
    "a|k": 5,
    "^^^^|k": 5,
    "^^^|k": 6,
    "^^|k": 8,
    "o|$$": 2,
    "f|$": 7,
    "q|6": 6,
    "6|f": 16,
    "f|$$": 4,
    "a|$$": 1,
    "r|$$$": 2,
    "t|S": 20,
    "p|o": 12,
    "^^^|t": 25,
    "6|K": 13,
    "S|s": 3,
    "s|o": 10,
    "d|S": 14,
    "l|S": 15,
    "y|C": 13,
    "2|s": 2,
    "m|$$": 80,
    "2|T": 1,
    "d|k": 2,
    "C|r": 1,
    "o|K": 16,
    "l|k": 71,
    "a|s": 13,
    "n|$$$": 12,
    "6|F": 1,
    "F|y": 4,
    "7|f": 3,
    "l|a": 33,
    "k|S": 22,
    "6|C": 12,
    "1|k": 4,
    "T|7": 2,
    "6|a": 10,
    "o|8": 4,
    "8|o": 1,
    "^|K": 14,
    "m|$$$": 7,
    "m|$$$$": 5,
    "^|P": 8,
    "P|o": 2,
    "o|1": 3,
    "k|d": 4,
    "l|f": 5,
    "^^^^|t": 8,
    "r|d": 9,
    "^^|l": 13,
    "^|f": 18,
    "f|a": 21,
    "C|a": 17,
    "K|d": 14,
    "d|l": 6,
    "r|l": 1,
    "S|K": 7,
    "l|t": 6,
    "S|k": 6,
    "y|l": 1,
    "o|T": 12,
    "y|o": 3,
    "l|l": 1,
    "s|y": 5,
    "m|g": 1,
    "y|y": 3,
    "^^|C": 6,
    "C|t": 10,
    "S|$": 5,
    "T|d": 5,
    "o|C": 8,
    "C|T": 13,
    "s|p": 1,
    "l|r": 1,
    "P|y": 3,
    "C|S": 1,
    "f|y": 5,
    "7|p": 4,
    "d|$$": 11,
    "r|S": 3,
    "^|8": 5,
    "8|d": 7,
    "6|g": 2,
    "8|$": 1,
    "C|F": 2,
    "1|s": 1,
    "o|g": 1,
    "6|n": 1,
    "C|l": 2,
    "k|l": 1,
    "f|d": 1,
    "2|$": 1,
    "K|o": 2,
    "K|F": 1,
    "r|o": 13,
    "a|g": 5,
    "y|a": 1,
    "1|g": 1,
    "^|F": 2,
    "F|d": 1,
    "d|g": 2,
    "a|a": 1,
    "1|t": 1,
    "1|m": 4,
    "m|y": 1,
    "l|7": 2,
    "s|7": 2,
    "C|p": 2,
    "a|y": 1,
    "d|p": 1,
    "^^^|S": 1,
    "s|S": 1,
    "d|$$$": 1,
    "d|$$$$": 1,
    "F|6": 2,
    "C|P": 1,
    "P|6": 6,
    "o|P": 3,
    "o|3": 2,
    "S|8": 1,
    "8|k": 1,
    "d|8": 1,
    "n|$$$$": 4,
    "6|$$": 1,
    "s|k": 2,
    "m|a": 1,
    "o|m": 2,
    "8|s": 2,
    "x|$": 1,
    "C|x": 1,
    "o|o": 7,
    "^|x": 5,
    "x|o": 3,
    "^|m": 3,
    "^^|x": 1,
    "1|f": 1,
    "f|6": 1,
    "K|a": 2,
    "^^|a": 6,
    "^^^|o": 3,
    "T|a": 2,
    "d|r": 1,
    "d|d": 1,
    "P|7": 1,
    "7|g": 1,
    "p|8": 1,
    "r|2": 2,
    "1|p": 2,
    "r|1": 1,
    "x|a": 2,
    "d|2": 1,
    "6|l": 1,
    "a|n": 5,
    "n|y": 1,
    "C|$": 2,
    "s|l": 1,
    "o|F": 1,
    "T|o": 2,
    "2|d": 1,
    "q|T": 1,
    "t|F": 1,
    "^^^^|o": 1,
    "1|d": 1,
    "a|K": 1,
    "s|d": 2,
    "m|d": 1,
    "a|t": 1,
    "F|o": 1,
    "o|2": 2,
    "^^^^|C": 1,
    "^^^|C": 1
  },
  "probabilities": {
    "^|p": 0.015561959654178675,
    "y|$": 0.7620889748549323,
    "p|S": 0.06666666666666667,
    "S|6": 0.4972972972972973,
    "6|o": 0.19351669941060903,
    "o|k": 0.29894620077648365,
    "k|y": 0.10095238095238095,
    "^|o": 0.23602305475504323,
    "r|$": 0.828080229226361,
    "o|d": 0.13754853022739877,
    "d|a": 0.2753807106598985,
    "a|2": 0.2832980972515856,
    "2|r": 0.03931203931203931,
    "^|q": 0.09827089337175793,
    "q|o": 0.9794721407624634,
    "o|y": 0.004991680532445923,
    "d|$": 0.0450507614213198,
    "o|f": 0.01608430393788131,
    "f|S": 0.03409090909090909,
    "S|o": 0.14054054054054055,
    "^|C": 0.16887608069164264,
    "C|y": 0.06332992849846783,
    "y|p": 0.00918762088974855,
    "p|C": 0.5259259259259259,
    "C|6": 0.4167517875383044,
    "6|y": 0.13555992141453832,
    "^|y": 0.0760806916426513,
    "6|d": 0.4449901768172888,
    "d|y": 0.6021573604060914,
    "^|a": 0.0717579250720461,
    "n|$": 0.8781725888324873,
    "a|1": 0.12544045102184637,
    "1|n": 0.6318681318681318,
    "o|$": 0.03438713255684969,
    "C|o": 0.10214504596527069,
    "f|o": 0.07954545454545454,
    "6|p": 0.015717092337917484,
    "p|d": 0.037037037037037035,
    "^^^^|p": 0.53125,
    "^^^|p": 0.45454545454545453,
    "^^|p": 0.10344827586206896,
    "y|$$": 0.07011605415860735,
    "^|d": 0.10028818443804034,
    "d|C": 0.01713197969543147,
    "2|n": 0.9484029484029484,
    "a|d": 0.004933051444679351,
    "d|7": 0.0031725888324873096,
    "7|o": 0.15412186379928317,
    "y|k": 0.0609284332688588,
    "k|6": 0.21523809523809523,
    "6|T": 0.005893909626719057,
    "T|6": 0.30357142857142855,
    "y|t": 0.039651837524177946,
    "t|6": 0.2283464566929134,
    "^|l": 0.017002881844380403,
    "s|$": 0.6260869565217392,
    "l|s": 0.02346041055718475,
    "^^|d": 0.15915119363395225,
    "s|$$": 0.07391304347826087,
    "o|a": 0.00776483638380477,
    "^|S": 0.07636887608069164,
    "S|T": 0.010810810810810811,
    "T|y": 0.5,
    "^|T": 0.00547550432276657,
    "o|l": 0.17415418746533556,
    "l|o": 0.06158357771260997,
    "k|7": 0.13047619047619047,
    "7|d": 0.3835125448028674,
    "l|C": 0.05865102639296188,
    "l|$": 0.4662756598240469,
    "a|l": 0.18675123326286117,
    "S|7": 0.0972972972972973,
    "7|y": 0.27598566308243727,
    "^|s": 0.025648414985590777,
    "^^|o": 0.08753315649867374,
    "o|s": 0.02384914032168608,
    "6|k": 0.09528487229862476,
    "m|$": 0.5471698113207547,
    "a|m": 0.07822410147991543,
    "l|d": 0.08797653958944282,
    "^^|q": 0.07161803713527852,
    "s|a": 0.16956521739130434,
    "^|7": 0.0011527377521613833,
    "^^|s": 0.058355437665782495,
    "^|r": 0.00345821325648415,
    "r|C": 0.01002865329512894,
    "^^|r": 0.002652519893899204,
    "y|$$$": 0.0183752417794971,
    "a|r": 0.28752642706131076,
    "C|s": 0.006128702757916241,
    "s|6": 0.013043478260869565,
    "d|s": 0.0012690355329949238,
    "a|$": 0.0028188865398167725,
    "S|a": 0.013513513513513514,
    "p|$": 0.037037037037037035,
    "y|f": 0.005802707930367505,
    "f|C": 0.4431818181818182,
    "r|$$": 0.03868194842406877,
    "o|t": 0.13422074320576816,
    "t|7": 0.07874015748031496,
    "k|$": 0.01904761904761905,
    "^|t": 0.03976945244956772,
    "t|C": 0.15748031496062992,
    "o|S": 0.0022185246810870773,
    "S|y": 0.062162162162162166,
    "C|d": 0.23186925434116445,
    "C|K": 0.05515832482124617,
    "K|y": 0.6448598130841121,
    "7|C": 0.007168458781362007,
    "^^|t": 0.20689655172413793,
    "6|$": 0.009823182711198428,
    "6|s": 0.015717092337917484,
    "t|a": 0.2736220472440945,
    "^^|S": 0.03978779840848806,
    "l|$$": 0.030791788856304986,
    "l|$$$": 0.008797653958944282,
    "l|$$$$": 0.004398826979472141,
    "r|y": 0.024355300859598854,
    "a|3": 0.007751937984496124,
    "3|n": 1.0,
    "C|7": 0.0449438202247191,
    "7|t": 0.017921146953405017,
    "t|y": 0.08464566929133858,
    "1|r": 0.2802197802197802,
    "o|p": 0.019966722129783693,
    "p|y": 0.05925925925925926,
    "S|d": 0.11891891891891893,
    "r|a": 0.054441260744985676,
    "^|6": 0.0020172910662824206,
    "6|t": 0.022593320235756387,
    "o|r": 0.0992789794786467,
    "1|6": 0.005494505494505495,
    "l|y": 0.06158357771260997,
    "y|s": 0.0014506769825918763,
    "p|a": 0.17037037037037037,
    "k|C": 0.08666666666666667,
    "^|g": 0.00028818443804034583,
    "g|$": 0.5185185185185185,
    "g|$$": 0.48148148148148145,
    "y|K": 0.0009671179883945841,
    "K|6": 0.17757009345794392,
    "d|o": 0.02601522842639594,
    "k|a": 0.36857142857142855,
    "^^|y": 0.18037135278514588,
    "n|$$": 0.09306260575296109,
    "k|o": 0.045714285714285714,
    "t|o": 0.1220472440944882,
    "o|7": 0.0033277870216306157,
    "^|k": 0.04610951008645533,
    "s|C": 0.013043478260869565,
    "7|k": 0.03942652329749104,
    "t|$": 0.013779527559055118,
    "o|6": 0.008319467554076539,
    "7|s": 0.06093189964157706,
    "C|k": 0.026557711950970377,
    "k|8": 0.007619047619047619,
    "8|y": 0.4,
    "y|S": 0.0038684719535783366,
    "6|S": 0.004911591355599214,
    "p|6": 0.007407407407407408,
    "y|d": 0.008220502901353965,
    "y|$$$$": 0.00918762088974855,
    "d|6": 0.0031725888324873096,
    "7|$": 0.03225806451612903,
    "a|k": 0.0035236081747709656,
    "^^^^|k": 0.15625,
    "^^^|k": 0.09090909090909091,
    "^^|k": 0.021220159151193633,
    "o|$$": 0.0011092623405435386,
    "f|$": 0.07954545454545454,
    "q|6": 0.017595307917888565,
    "6|f": 0.015717092337917484,
    "f|$$": 0.045454545454545456,
    "a|$$": 0.0007047216349541931,
    "r|$$$": 0.0028653295128939827,
    "t|S": 0.03937007874015748,
    "p|o": 0.08888888888888889,
    "^^^|t": 0.3787878787878788,
    "6|K": 0.012770137524557957,
    "S|s": 0.008108108108108109,
    "s|o": 0.043478260869565216,
    "d|S": 0.008883248730964468,
    "l|S": 0.021994134897360705,
    "y|C": 0.006286266924564797,
    "2|s": 0.004914004914004914,
    "m|$$": 0.37735849056603776,
    "2|T": 0.002457002457002457,
    "d|k": 0.0012690355329949238,
    "C|r": 0.0010214504596527069,
    "o|K": 0.00887409872434831,
    "l|k": 0.10410557184750734,
    "a|s": 0.009161381254404511,
    "n|$$$": 0.02030456852791878,
    "6|F": 0.0009823182711198428,
    "F|y": 0.5,
    "7|f": 0.010752688172043012,
    "l|a": 0.04838709677419355,
    "k|S": 0.02095238095238095,
    "6|C": 0.011787819253438114,
    "1|k": 0.02197802197802198,
    "T|7": 0.03571428571428571,
    "6|a": 0.009823182711198428,
    "o|8": 0.0022185246810870773,
    "8|o": 0.05,
    "^|K": 0.004034582132564841,
    "m|$$$": 0.0330188679245283,
    "m|$$$$": 0.02358490566037736,
    "^|P": 0.0023054755043227667,
    "P|o": 0.16666666666666666,
    "o|1": 0.0016638935108153079,
    "k|d": 0.0038095238095238095,
    "l|f": 0.007331378299120235,
    "^^^^|t": 0.25,
    "r|d": 0.012893982808022923,
    "^^|l": 0.034482758620689655,
    "^|f": 0.005187319884726225,
    "f|a": 0.23863636363636365,
    "C|a": 0.017364657814096015,
    "K|d": 0.1308411214953271,
    "d|l": 0.0038071065989847717,
    "r|l": 0.0014326647564469914,
    "S|K": 0.01891891891891892,
    "l|t": 0.008797653958944282,
    "S|k": 0.016216216216216217,
    "y|l": 0.00048355899419729207,
    "o|T": 0.0066555740432612314,
    "y|o": 0.0014506769825918763,
    "l|l": 0.001466275659824047,
    "s|y": 0.021739130434782608,
    "m|g": 0.0047169811320754715,
    "y|y": 0.0014506769825918763,
    "^^|C": 0.015915119363395226,
    "C|t": 0.010214504596527068,
    "S|$": 0.013513513513513514,
    "T|d": 0.08928571428571429,
    "o|C": 0.004437049362174155,
    "C|T": 0.013278855975485188,
    "s|p": 0.004347826086956522,
    "l|r": 0.001466275659824047,
    "P|y": 0.25,
    "C|S": 0.0010214504596527069,
    "f|y": 0.056818181818181816,
    "7|p": 0.014336917562724014,
    "d|$$": 0.006979695431472081,
    "r|S": 0.004297994269340974,
    "^|8": 0.001440922190201729,
    "8|d": 0.35,
    "6|g": 0.0019646365422396855,
    "8|$": 0.05,
    "C|F": 0.0020429009193054137,
    "1|s": 0.005494505494505495,
    "o|g": 0.0005546311702717693,
    "6|n": 0.0009823182711198428,
    "C|l": 0.0020429009193054137,
    "k|l": 0.0009523809523809524,
    "f|d": 0.011363636363636364,
    "2|$": 0.002457002457002457,
    "K|o": 0.018691588785046728,
    "K|F": 0.009345794392523364,
    "r|o": 0.01862464183381089,
    "a|g": 0.0035236081747709656,
    "y|a": 0.00048355899419729207,
    "1|g": 0.005494505494505495,
    "^|F": 0.0005763688760806917,
    "F|d": 0.125,
    "d|g": 0.0012690355329949238,
    "a|a": 0.0007047216349541931,
    "1|t": 0.005494505494505495,
    "1|m": 0.02197802197802198,
    "m|y": 0.0047169811320754715,
    "l|7": 0.002932551319648094,
    "s|7": 0.008695652173913044,
    "C|p": 0.0020429009193054137,
    "a|y": 0.0007047216349541931,
    "d|p": 0.0006345177664974619,
    "^^^|S": 0.015151515151515152,
    "s|S": 0.004347826086956522,
    "d|$$$": 0.0006345177664974619,
    "d|$$$$": 0.0006345177664974619,
    "F|6": 0.25,
    "C|P": 0.0010214504596527069,
    "P|6": 0.5,
    "o|P": 0.0016638935108153079,
    "o|3": 0.0011092623405435386,
    "S|8": 0.002702702702702703,
    "8|k": 0.05,
    "d|8": 0.0006345177664974619,
    "n|$$$$": 0.00676818950930626,
    "6|$$": 0.0009823182711198428,
    "s|k": 0.008695652173913044,
    "m|a": 0.0047169811320754715,
    "o|m": 0.0011092623405435386,
    "8|s": 0.1,
    "x|$": 0.16666666666666666,
    "C|x": 0.0010214504596527069,
    "o|o": 0.003882418191902385,
    "^|x": 0.001440922190201729,
    "x|o": 0.5,
    "^|m": 0.0008645533141210375,
    "^^|x": 0.002652519893899204,
    "1|f": 0.005494505494505495,
    "f|6": 0.011363636363636364,
    "K|a": 0.018691588785046728,
    "^^|a": 0.015915119363395226,
    "^^^|o": 0.045454545454545456,
    "T|a": 0.03571428571428571,
    "d|r": 0.0006345177664974619,
    "d|d": 0.0006345177664974619,
    "P|7": 0.08333333333333333,
    "7|g": 0.0035842293906810036,
    "p|8": 0.007407407407407408,
    "r|2": 0.0028653295128939827,
    "1|p": 0.01098901098901099,
    "r|1": 0.0014326647564469914,
    "x|a": 0.3333333333333333,
    "d|2": 0.0006345177664974619,
    "6|l": 0.0009823182711198428,
    "a|n": 0.0035236081747709656,
    "n|y": 0.001692047377326565,
    "C|$": 0.0020429009193054137,
    "s|l": 0.004347826086956522,
    "o|F": 0.0005546311702717693,
    "T|o": 0.03571428571428571,
    "2|d": 0.002457002457002457,
    "q|T": 0.002932551319648094,
    "t|F": 0.001968503937007874,
    "^^^^|o": 0.03125,
    "1|d": 0.005494505494505495,
    "a|K": 0.0007047216349541931,
    "s|d": 0.008695652173913044,
    "m|d": 0.0047169811320754715,
    "a|t": 0.0007047216349541931,
    "F|o": 0.125,
    "o|2": 0.0011092623405435386,
    "^^^^|C": 0.03125,
    "^^^|C": 0.015151515151515152
  },
  "char_counts": {
    "p": 135,
    "S": 370,
    "6": 1017,
    "o": 1801,
    "k": 1050,
    "y": 1866,
    "d": 1563,
    "a": 1418,
    "2": 407,
    "r": 669,
    "q": 341,
    "f": 84,
    "C": 979,
    "1": 182,
    "n": 520,
    "7": 279,
    "T": 56,
    "t": 508,
    "l": 652,
    "s": 213,
    "m": 120,
    "K": 107,
    "3": 13,
    "g": 14,
    "8": 20,
    "F": 8,
    "P": 12,
    "x": 6
  },
  "charset": [
    "1",
    "2",
    "3",
    "6",
    "7",
    "8",
    "C",
    "F",
    "K",
    "P",
    "S",
    "T",
    "a",
    "d",
    "f",
    "g",
    "k",
    "l",
    "m",
    "n",
    "o",
    "p",
    "q",
    "r",
    "s",
    "t",
    "x",
    "y",
    "$",
    "$$",
    "$$$",
    "$$$$",
    "^",
    "^^",
    "^^^",
    "^^^^"
  ],
  "pages": [
    {
      "folio": "f26r",
      "quire": "D",
      "language": "B",
      "hand": "2",
      "illustration": "H"
    },
    {
      "folio": "f26v",
      "quire": "D",
      "language": "B",
      "hand": "2",
      "illustration": "H"
    },
    {
      "folio": "f31r",
      "quire": "D",
      "language": "B",
      "hand": "2",
      "illustration": "H"
    },
    {
      "folio": "f31v",
      "quire": "D",
      "language": "B",
      "hand": "2",
      "illustration": "H"
    },
    {
      "folio": "f33r",
      "quire": "E",
      "language": "B",
      "hand": "2",
      "illustration": "H"
    },
    {
      "folio": "f33v",
      "quire": "E",
      "language": "B",
      "hand": "2",
      "illustration": "H"
    },
    {
      "folio": "f34r",
      "quire": "E",
      "language": "B",
      "hand": "2",
      "illustration": "H"
    },
    {
      "folio": "f34v",
      "quire": "E",
      "language": "B",
      "hand": "2",
      "illustration": "H"
    },
    {
      "folio": "f39r",
      "quire": "E",
      "language": "B",
      "hand": "2",
      "illustration": "H"
    },
    {
      "folio": "f39v",
      "quire": "E",
      "language": "B",
      "hand": "2",
      "illustration": "H"
    },
    {
      "folio": "f40r",
      "quire": "E",
      "language": "B",
      "hand": "2",
      "illustration": "H"
    },
    {
      "folio": "f40v",
      "quire": "E",
      "language": "B",
      "hand": "2",
      "illustration": "H"
    },
    {
      "folio": "f41r",
      "quire": "F",
      "language": "B",
      "hand": "2",
      "illustration": "H"
    },
    {
      "folio": "f41v",
      "quire": "F",
      "language": "B",
      "hand": "2",
      "illustration": "H"
    },
    {
      "folio": "f43r",
      "quire": "F",
      "language": "B",
      "hand": "2",
      "illustration": "H"
    },
    {
      "folio": "f43v",
      "quire": "F",
      "language": "B",
      "hand": "2",
      "illustration": "H"
    },
    {
      "folio": "f46r",
      "quire": "F",
      "language": "B",
      "hand": "2",
      "illustration": "H"
    },
    {
      "folio": "f46v",
      "quire": "F",
      "language": "B",
      "hand": "2",
      "illustration": "H"
    },
    {
      "folio": "f48r",
      "quire": "F",
      "language": "B",
      "hand": "2",
      "illustration": "H"
    },
    {
      "folio": "f48v",
      "quire": "F",
      "language": "B",
      "hand": "2",
      "illustration": "H"
    },
    {
      "folio": "f50r",
      "quire": "G",
      "language": "B",
      "hand": "2",
      "illustration": "H"
    },
    {
      "folio": "f50v",
      "quire": "G",
      "language": "B",
      "hand": "2",
      "illustration": "H"
    },
    {
      "folio": "f55r",
      "quire": "G",
      "language": "B",
      "hand": "2",
      "illustration": "H"
    },
    {
      "folio": "f55v",
      "quire": "G",
      "language": "B",
      "hand": "2",
      "illustration": "H"
    },
    {
      "folio": "f57r",
      "quire": "H",
      "language": "B",
      "hand": "2",
      "illustration": "H"
    },
    {
      "folio": "f66v",
      "quire": "H",
      "language": "B",
      "hand": "5",
      "illustration": "H"
    },
    {
      "folio": "f94r",
      "quire": "Q",
      "language": "B",
      "hand": "5",
      "illustration": "H"
    },
    {
      "folio": "f94v",
      "quire": "Q",
      "language": "B",
      "hand": "5",
      "illustration": "H"
    },
    {
      "folio": "f95r1",
      "quire": "Q",
      "language": "B",
      "hand": "5",
      "illustration": "H"
    },
    {
      "folio": "f95r2",
      "quire": "Q",
      "language": "B",
      "hand": "5",
      "illustration": "H"
    },
    {
      "folio": "f95v2",
      "quire": "Q",
      "language": "B",
      "hand": "5",
      "illustration": "H"
    },
    {
      "folio": "f95v1",
      "quire": "Q",
      "language": "B",
      "hand": "5",
      "illustration": "H"
    }
  ]
}